README.md
setup.py
xzero/__init__.py
xzero/algorithm.py
xzero.egg-info/PKG-INFO
xzero.egg-info/SOURCES.txt
xzero.egg-info/dependency_links.txt
xzero.egg-info/requires.txt
xzero.egg-info/top_level.txt
xzero/data_handler/__init__.py
xzero/data_handler/file_handler.py
xzero/data_handler/frame_handler.py
xzero/events/__init__.py
xzero/events/market.py
xzero/events/order.py
xzero/execution/__init__.py
xzero/execution/commission.py
xzero/execution/simu_exec.py
xzero/portfolio/__init__.py
xzero/portfolio/analyzer.py
xzero/portfolio/port.py
xzero/strategy/__init__.py
xzero/strategy/generic.py