Metadata-Version: 2.1
Name: xzero
Version: 0.0.1
Summary: python backtest toolkit
Home-page: https://github.com/alpha-xone/xzero
Author: Alpha
License: Apache 2
Keywords: python backtest trading
Platform: UNKNOWN
Classifier: Programming Language :: Python :: 3
Classifier: License :: OSI Approved :: Apache Software License
Classifier: Operating System :: OS Independent
Provides-Extra: all
